__init__.py
deltalake_redis_lock.py
global_lock.py
redis_lock_object_store.py
deltalake_redis_lock-0.0.1a11.dist-info/LICENSE
deltalake_redis_lock-0.0.1a11.dist-info/WHEEL
deltalake_redis_lock-0.0.1a11.dist-info/METADATA
deltalake_redis_lock-0.0.1a11.dist-info/RECORD
