Metadata-Version: 2.1
Name: deltalake-redis-lock
Version: 0.0.1a11
Summary: deltalake-redis-lock
Home-page: https://github.com/wrapbytes/deltalake-redis-lock
License: MIT
Author: Simon Thelin
Requires-Python: >=3.9,<3.12
Classifier: License :: OSI Approved :: MIT License
Classifier: Programming Language :: Python :: 3
Classifier: Programming Language :: Python :: 3.10
Classifier: Programming Language :: Python :: 3.9
Requires-Dist: deltalake (>=0.13.0,<0.14.0)
Requires-Dist: pandas (>=2.1.3,<3.0.0)
Requires-Dist: pyarrow (>=14.0.1,<15.0.0)
Requires-Dist: redis (>=5.0.1,<6.0.0)
Project-URL: Repository, https://github.com/wrapbytes/deltalake-redis-lock
